{
  "software_name": "anaconda3_x86_64",
  "comprehensive_overview": "Anaconda is a free, open-source distribution of Python and R programming languages for scientific computing, that aims to simplify package management and deployment. It includes hundreds of popular data science, machine learning, and scientific computing packages.",
  "core_features": "1. Simplified package management through conda package manager. 2. Includes popular data science and machine learning libraries like Numpy, Pandas, Scikit-learn, TensorFlow, etc. 3. Enables easy creation of virtual environments for different projects. 4. Jupyter notebook integration for interactive coding and data visualization. 5. Supports Windows, macOS, and Linux platforms.",
  "general_tags": ["software distribution", "scientific computing", "data science", "machine learning"],
  "additional_tags": {
    "research_discipline": [],
    "research_area": [],
    "software_class": "Package Manager",
    "software_type": "Distribution",
    "field_of_science": "Other Computer and Information Sciences"
  }
}