{
    "software_name": "debreak",
    "comprehensive_overview": "debreak is a tool for analyzing and visualizing the output generated by the debarcoder software. Debarcoder is used for decoding high-throughput sequencing data from combinatorial CRISPR screens.",
    "core_features": "debreak allows users to easily interpret the results of debarcoder by providing visualization and statistical analysis tools. It helps in understanding the performance of the CRISPR screen and identifying significant hits.",
    "general_tags": ["bioinformatics", "HPC tools"],
    "research_discipline": "",
    "research_area": "",
    "software_class": "Analysis Tool",
    "software_type": "Bioinformatics Tool",
    "field_of_science": "Biological Sciences"
}