{
    "software_name": "enchant-2",
    "comprehensive_overview": "Enchant is a spellchecking library that provides a consistent API for invoking spellchecking routines across different platforms. Enchant-2 is the newer version of the Enchant spellchecking framework.",
    "core_features": "1. Cross-platform spellchecking capabilities. 2. Consistent API for invoking spellchecking routines. 3. Supports multiple backends for spellchecking. 4. Customizable dictionaries and language support.",
    "general_tags": ["spellchecking", "library", "cross-platform", "spellchecking routines"],
    "additional_tags": {
        "research_discipline": "",
        "research_area": "",
        "software_class": "Spellchecking Library",
        "software_type": "Spellchecking",
        "field_of_science": "Computer and Information Sciences"
    }
}