{
    "software_name": "GC",
    "overview": "GC is a compiler for the Go programming language.",
    "core_features": "GC provides garbage collection, concurrency support, memory safety, and a standard library.",
    "general_tags": ["compiler", "Go", "garbage collection", "concurrency"],
    "additional_tags": {
        "research_discipline": "Computer Science",
        "research_area": "Software Engineering, Systems, and Development",
        "software_class": "Compiler",
        "software_type": "Programming Language Compiler",
        "field_of_science": [
            "Computer and Information Sciences",
            "Computer Science"
        ]
    }
}