{
    "software_name": "KneadData",
    "comprehensive_overview": "KneadData is a tool designed to perform quality control on metagenomic and metatranscriptomic sequencing data, specifically targeted at removing contaminating host sequences and improving the data quality for downstream analysis.",
    "core_features": [
        "Quality control for metagenomic and metatranscriptomic data",
        "Removal of contaminating host sequences",
        "Improvement of data quality for downstream analysis",
        "Support for various sequencing platforms",
        "Customizable parameters for quality filtering"
    ],
    "general_tags": [
        "Bioinformatics",
        "Metagenomics",
        "Data Quality Control"
    ],
    "research_discipline": "Biomolecular Sciences",
    "research_area": "Metagenomics",
    "software_class": "Bioinformatics Tool",
    "software_type": "Analysis Tool",
    "field_of_science": "Biological Sciences"
}