{
    "software_name": "libfabric",
    "comprehensive_overview": "libfabric is a high-performance library for fabric interfaces, designed to abstract fabric communication resources to applications while providing flexibility to applications that need to bypass the fabric interfaces. It provides fabric-agnostic interfaces for communication in high-performance computing (HPC) environments.",
    "core_features": "1. Abstraction of fabric interfaces for applications\n2. Flexibility for applications to bypass fabric interfaces\n3. Fabric-agnostic interfaces for HPC communication\n4. High-performance communication resources",
    "general_tags": ["fabric interfaces", "high-performance computing", "communication resources"],
    "additional_tags": {
        "research_discipline": "Computer Science",
        "research_area": "Software Engineering, Systems, and Development",
        "software_class": "Library",
        "software_type": "Communication Library",
        "field_of_science": "Engineering and Technology"
    }
}