{
    "software_name": "Open MPI",
    "comprehensive_overview": "Open MPI (Message Passing Interface) is an open-source software implementation of the Message Passing Interface standard. It is designed for high-performance computing (HPC) and is used to parallelize and optimize applications across distributed computing systems.",
    "core_features": "1. Support for parallel computing across distributed memory systems\n2. Scalability for large computing clusters\n3. High performance and efficiency in message passing\n4. Flexibility in configuration and customization\n5. Fault tolerance and resilience in distributed computing environments",
    "general_tags": ["HPC", "Parallel Computing", "Message Passing Interface"],
    "additional_tags": {
        "research_discipline": [],
        "research_area": [],
        "software_class": "Middleware",
        "software_type": "Library",
        "field_of_science": []
    }
}