{
  "software_name": "Theano",
  "comprehensive_overview": "Theano is an open-source symbolic mathematical library, used for deep learning and numerical computation, that allows you to define, optimize, and evaluate mathematical expressions involving multi-dimensional arrays efficiently.",
  "core_features": "Theano provides modules for defining and manipulating mathematical expressions, supports GPU computation, enables automatic differentiation, optimizes symbolic graph execution, and integrates seamlessly with NumPy. It is commonly used for building and training deep learning models.",
  "general_tags": ["mathematical library", "deep learning", "numerical computation"],
  "research_discipline": "Artificial Intelligence and Intelligent Systems",
  "research_area": "Machine Learning",
  "software_class": "Library",
  "software_type": "Symbolic Mathematical Library",
  "field_of_science": "Computer and Information Sciences"
}