{
    "Software": "glibc",
    "AI Description": "glibc, the GNU C Library, is an essential part of most systems running the Linux kernel. It provides the necessary functionality for programs written in the C programming language to interact with the operating system and hardware.",
    "Core Features": "Implementation Of The Standard C Library Functions, System Calls & Low-Level Interfaces, Dynamic Memory Allocation & Management, Thread Support & Synchronization, Localization Support",
    "General Tags": "C Library, Operating System, System Programming",
    "Software Type": "Library",
    "Software Class": "System Library",
    "Research Area": "Systems Programming",
    "Research Discipline": "Computer & Information Sciences",
    "Research Field": "Computer & Information Sciences"
}