{
    "Software": "IDL",
    "AI Description": "IDL (Interactive Data Language) is a programming language used for data analysis, visualization, and application development. It provides a comprehensive set of tools for scientific research and data processing.",
    "Core Features": "IDL offers a wide range of mathematical functions, statistical analysis tools, image processing capabilities, and interactive graphics for data visualization. It supports data input/output operations, array handling, and extensive libraries for various scientific and engineering applications.",
    "General Tags": [
        "Software",
        "Data Analysis",
        "Data Visualization",
        "Scientific Research"
    ],
    "Software Type": "Programming Language",
    "Software Class": "Data Analysis & Visualization",
    "Research Field": "Physical Sciences",
    "Research Area": "",
    "Research Discipline": ""
}