{
    "Software": "PyTorch",
    "AI Description": "PyTorch is an open-source machine learning library used for numerical computations and building deep learning models.",
    "Core Features": [
        "Dynamic computation graph",
        "GPU acceleration",
        "Automatic differentiation",
        "Support for complex neural networks"
    ],
    "General Tags": [
        "Machine Learning",
        "Deep Learning",
        "Numerical Computation",
        "Neural Networks"
    ],
    "Software Type": "Machine Learning Framework",
    "Software Class": "Library",
    "Research Field": "Computer & Information Sciences",
    "Research Area": "Deep Learning",
    "Research Discipline": "Artificial Intelligence & Intelligent Systems"
}