{
    "Software": "rasterio",
    "AI Description": "Rasterio is a Python library for reading and writing geospatial raster datasets. It is built on the capabilities of the GDAL (Geospatial Data Abstraction Library) and provides easy access to the functionalities for opening, reading, and writing geospatial raster data formats.",
    "Core Features": [
        "Read and write geospatial raster datasets",
        "Access metadata and geospatial information of raster datasets",
        "Manipulate raster data through various functions and operations",
        "Integration with other geospatial libraries and tools"
    ],
    "General Tags": [
        "Python Library",
        "Geospatial Data",
        "Raster Data",
        "Gdal",
        "Remote Sensing"
    ],
    "Software Type": "Data Processing/Analysis",
    "Software Class": "Libraries",
    "Research Field": "Earth & Environmental Sciences",
    "Research Area": "",
    "Research Discipline": ""
}