{
    "Software": "odgi",
    "AI Description": "odgi is a succinct graphical representation of variation graphs. It provides methods for dynamic histogram-based organization and interactive visualization of large-scale structural variant graphs.",
    "Core Features": "Efficient Graphical Representation Of Variation Graphs, Dynamic Histogram-Based Organization, Interactive Visualization Of Large-Scale Structural Variant Graphs",
    "General Tags": "Graph Visualization, Structural Variation Analysis, Genomics",
    "Software Type": "Bioinformatics",
    "Software Class": "Analysis Tool",
    "Research Area": "",
    "Research Discipline": "",
    "Research Field": "Biological Sciences"
}